tgvoip_pyrogram/__init__.py
tgvoip_pyrogram/base_call.py
tgvoip_pyrogram/file_stream_call.py
tgvoip_pyrogram/incoming_call.py
tgvoip_pyrogram/native_io_call.py
tgvoip_pyrogram/outgoing_call.py
tgvoip_pyrogram/service.py
pytgvoip_pyrogram-0.0.8.dist-info/COPYING
pytgvoip_pyrogram-0.0.8.dist-info/COPYING.lesser
pytgvoip_pyrogram-0.0.8.dist-info/METADATA
pytgvoip_pyrogram-0.0.8.dist-info/NOTICE
pytgvoip_pyrogram-0.0.8.dist-info/WHEEL
pytgvoip_pyrogram-0.0.8.dist-info/top_level.txt
pytgvoip_pyrogram-0.0.8.dist-info/RECORD
