Metadata-Version: 2.1
Name: pytgvoip-pyrogram
Version: 0.0.8
Summary: Pyrogram support module for Telegram VoIP Library for Python
Home-page: https://github.com/bakatrouble/pytgvoip_pyrogram
Author: bakatrouble
Author-email: bakatrouble@gmail.com
License: LGPLv3+
Project-URL: Tracker, https://github.com/bakatrouble/pytgvoip_pyrogram/issues
Project-URL: Community, https:/t.me/pytgvoip
Project-URL: Source, https://github.com/bakatrouble/pytgvoip_pyrogram
Keywords: telegram messenger voip library python pyrogram
Platform: UNKNOWN
Classifier: Development Status :: 3 - Alpha
Classifier: Intended Audience :: Developers
Classifier: License :: OSI Approved :: GNU Lesser General Public License v3 or later (LGPLv3+)
Classifier: Operating System :: OS Independent
Classifier: Programming Language :: Python
Classifier: Programming Language :: Python :: 3
Classifier: Programming Language :: Python :: 3 :: Only
Classifier: Programming Language :: Python :: 3.4
Classifier: Programming Language :: Python :: 3.5
Classifier: Programming Language :: Python :: 3.6
Classifier: Programming Language :: Python :: 3.7
Classifier: Programming Language :: Python :: Implementation
Classifier: Programming Language :: Python :: Implementation :: CPython
Classifier: Topic :: Internet
Classifier: Topic :: Communications
Classifier: Topic :: Communications :: Internet Phone
Classifier: Topic :: Software Development :: Libraries
Classifier: Topic :: Software Development :: Libraries :: Python Modules
Requires-Dist: pyrogram (>=0.16.0)
Requires-Dist: pytgvoip (>=0.0.7)
